MANIFEST.in
README.md
requirements-dev.txt
requirements.txt
setup.cfg
setup.py
versioneer.py
WOFpy.egg-info/PKG-INFO
WOFpy.egg-info/SOURCES.txt
WOFpy.egg-info/dependency_links.txt
WOFpy.egg-info/entry_points.txt
WOFpy.egg-info/not-zip-safe
WOFpy.egg-info/requires.txt
WOFpy.egg-info/top_level.txt
wof/WaterML.py
wof/WaterML_1_1.py
wof/WofWsdls.py
wof/__init__.py
wof/_version.py
wof/core.py
wof/core_1_0.py
wof/core_1_1.py
wof/dao.py
wof/models.py
wof/vocabularies.py
wof/wofpy_config.py
wof/apps/__init__.py
wof/apps/spyned_1_0.py
wof/apps/spyned_1_1.py
wof/apps/waterml2.py
wof/examples/__init__.py
wof/examples/flask/__init__.py
wof/examples/flask/runserver_multiple.py
wof/examples/flask/cbi/__init__.py
wof/examples/flask/cbi/build_cbi_cache.py
wof/examples/flask/cbi/cbi_cache_models.py
wof/examples/flask/cbi/cbi_config.cfg
wof/examples/flask/cbi/cbi_dao.py
wof/examples/flask/cbi/cbi_models.py
wof/examples/flask/cbi/cbi_sos_client.py
wof/examples/flask/cbi/cbi_sos_parser.py
wof/examples/flask/cbi/runserver_cbi.py
wof/examples/flask/odm2/__init__.py
wof/examples/flask/odm2/cvmap_wml_1_1.yml
wof/examples/flask/odm2/runserver_multiple.py
wof/examples/flask/odm2/measurement/__init__.py
wof/examples/flask/odm2/measurement/odm2_config_measurement.cfg
wof/examples/flask/odm2/measurement/odm2_measurement_dao.py
wof/examples/flask/odm2/measurement/runserver_odm2_measurement.py
wof/examples/flask/odm2/measurement/sqlalch_odm2_models.py
wof/examples/flask/odm2/timeseries/__init__.py
wof/examples/flask/odm2/timeseries/odm2_config_timeseries.cfg
wof/examples/flask/odm2/timeseries/odm2_timeseries_dao.py
wof/examples/flask/odm2/timeseries/runserver_multiple_odm2timeseries.py
wof/examples/flask/odm2/timeseries/runserver_odm2_timeseries.py
wof/examples/flask/odm2/timeseries/sqlalch_odm2_models.py
wof/examples/flask/odm2/timeseries/watermlcvs.json
wof/examples/flask/swis/__init__.py
wof/examples/flask/swis/runserver_swis.py
wof/examples/flask/swis/sqlalch_swis_models.py
wof/examples/flask/swis/swis2.db
wof/examples/flask/swis/swis_config.cfg
wof/examples/flask/swis/swis_dao.py
wof/examples/production_configs/wofpy
wof/examples/production_configs/wofpy.conf
