Metadata-Version: 1.1
Name: WOFpy
Version: 2.3.0
Summary: a python library for serving WaterOneFlow web services
Home-page: UNKNOWN
Author: Emilio Mayorga
Author-email: emiliom@uw.edu
License: BSD
Keywords: cuahsi his wofpy water waterml cuahsi wateroneflow odm2
Platform: any
Classifier: Development Status :: 4 - Beta
Classifier: Intended Audience :: Science/Research
Classifier: License :: OSI Approved :: BSD License
Classifier: Operating System :: OS Independent
Classifier: Programming Language :: Python
Classifier: Programming Language :: Python :: 2.7
Classifier: Programming Language :: Python :: 3.4
Classifier: Programming Language :: Python :: 3.5
Classifier: Programming Language :: Python :: 3.6
Classifier: Topic :: Software Development :: Libraries :: Python Modules
